pybravia/__init__.py
pybravia/client.py
pybravia/const.py
pybravia/exceptions.py
pybravia/py.typed
pybravia/util.py
pybravia-0.4.1.dist-info/METADATA
pybravia-0.4.1.dist-info/WHEEL
pybravia-0.4.1.dist-info/licenses/LICENSE
pybravia-0.4.1.dist-info/RECORD
