Metadata-Version: 2.4
Name: pybravia
Version: 0.4.1
Summary: Python async library for remote control of Sony Bravia TVs 2013 and newer.
Author: Artem Draft
License: MIT
License-File: LICENSE
Requires-Python: >=3.10
Requires-Dist: aiohttp>=3.8
Requires-Dist: yarl
